Metadata-Version: 2.1
Name: immin5-api
Version: 1.10.4.1.dev2
Summary: SpaceONE API Protobuf
Home-page: https://www.spaceone.dev/
Author: MEGAZONE SpaceONE Team
Author-email: admin@spaceone.dev
License: Apache Software License
